herakles/__init__.py
herakles/auth.py
herakles/issue_wrapper.py
herakles/jira_date_parser.py
herakles/jira_response_iterable.py
herakles/jira_wrapper.py
herakles/jql/__init__.py
herakles/jql/jql_builder.py
herakles/util/__init__.py
herakles/util/file_utils.py
herakles-0.1.7.dist-info/LICENSE
herakles-0.1.7.dist-info/WHEEL
herakles-0.1.7.dist-info/METADATA
herakles-0.1.7.dist-info/RECORD
