Metadata-Version: 2.1
Name: herakles
Version: 0.1.7
Summary: Tools for working with the python jira client.
Home-page: https://github.com/dbradf/herakles-jira-client
License: Apache-2.0
Author: David Bradford
Author-email: david.bradford@mongodb.com
Requires-Python: >=3.7,<4.0
Classifier: License :: OSI Approved :: Apache Software License
Classifier: Programming Language :: Python :: 3
Classifier: Programming Language :: Python :: 3.7
Classifier: Programming Language :: Python :: 3.8
Requires-Dist: PyYaml (>=5.0,<6.0)
Requires-Dist: jira (>=2.0,<3.0)
Project-URL: Repository, https://github.com/dbradf/herakles-jira-client
